Metadata-Version: 2.1
Name: simple-fpdf
Version: 0.1.0
Summary: Simple FPDF
Home-page: https://github.com/alexander-schillemans/simple-fpdf
Author: Alexander Schillemans
Author-email: alexander.schillemans@hotmail.com
License: GPL-3.0-or-later
Download-URL: https://github.com/alexander-schillemans/simple-fpdf/archive/refs/tags/0.1.0.tar.gz
Keywords: pdf,fpdf,simple_fpdf
Platform: UNKNOWN
Classifier: Development Status :: 3 - Alpha
Classifier: Intended Audience :: Developers
Classifier: Topic :: Software Development :: Build Tools
Classifier: License :: OSI Approved :: GNU General Public License v3 or later (GPLv3+)
Classifier: Programming Language :: Python :: 3.6
License-File: LICENSE.txt
